S3netCDF4/_Exceptions.c
S3netCDF4/_Exceptions.cpython-39-darwin.so
S3netCDF4/__init__.py
S3netCDF4/_s3netCDF4.c
S3netCDF4/_s3netCDF4.cpython-39-darwin.so
S3netCDF4/Backends/_s3FileObject.c
S3netCDF4/Backends/_s3FileObject.cpython-39-darwin.so
S3netCDF4/Backends/_s3aioFileObject.c
S3netCDF4/Backends/_s3aioFileObject.cpython-39-darwin.so
S3netCDF4/CFA/_CFAClasses.c
S3netCDF4/CFA/_CFAClasses.cpython-39-darwin.so
S3netCDF4/CFA/_CFAExceptions.c
S3netCDF4/CFA/_CFAExceptions.cpython-39-darwin.so
S3netCDF4/CFA/_CFASplitter.c
S3netCDF4/CFA/_CFASplitter.cpython-39-darwin.so
S3netCDF4/CFA/Parsers/_CFAParser.c
S3netCDF4/CFA/Parsers/_CFAParser.cpython-39-darwin.so
S3netCDF4/CFA/Parsers/_CFAnetCDFParser.c
S3netCDF4/CFA/Parsers/_CFAnetCDFParser.cpython-39-darwin.so
S3netCDF4/Managers/_ConfigManager.c
S3netCDF4/Managers/_ConfigManager.cpython-39-darwin.so
S3netCDF4/Managers/_ConnectionPool.c
S3netCDF4/Managers/_ConnectionPool.cpython-39-darwin.so
S3netCDF4/Managers/_FileManager.c
S3netCDF4/Managers/_FileManager.cpython-39-darwin.so
S3netCDF4-2.1rc1.dist-info/LICENSE
S3netCDF4-2.1rc1.dist-info/METADATA
S3netCDF4-2.1rc1.dist-info/WHEEL
S3netCDF4-2.1rc1.dist-info/top_level.txt
S3netCDF4-2.1rc1.dist-info/RECORD
