Metadata-Version: 2.1
Name: S3netCDF4
Version: 2.1rc1
Summary: A library to facilitate the storage of netCDF files on ObjectStores in an efficient manner.
Home-page: http://www.ceda.ac.uk/
Author: Neil Massey
Author-email: neil.massey@stfc.ac.uk
License: my License
Platform: UNKNOWN
Classifier: Development Status :: 4 - Beta
Classifier: Intended Audience :: Science/Research
Classifier: License :: OSI Approved :: BSD License
Classifier: Topic :: Software Development :: Libraries :: Python Modules
Classifier: Topic :: System :: Archiving :: Compression
Classifier: Operating System :: OS Independent
Classifier: Programming Language :: Python
Classifier: Programming Language :: Python :: 3
Classifier: Programming Language :: Python :: 3.7
Classifier: Programming Language :: Python :: 3.8
Classifier: Programming Language :: Python :: 3.9
Requires-Dist: numpy (>=1.19.0)
Requires-Dist: cython
Requires-Dist: netcdf4
Requires-Dist: botocore
Requires-Dist: aiobotocore
Requires-Dist: psutil
